dual/__init__.py
dual/__main__.py
dual/dual.py
dual/py.typed
dual-0.3.2.dist-info/METADATA
dual-0.3.2.dist-info/WHEEL
dual-0.3.2.dist-info/entry_points.txt
dual-0.3.2.dist-info/licenses/LICENSE
dual-0.3.2.dist-info/RECORD
