Metadata-Version: 2.3
Name: dual
Version: 0.3.2
Summary: `dual` is a package for dual problem.
Project-URL: homepage, https://github.com/SaitoTsutomu/dual
Author-email: Saito Tsutomu <tsutomu7@hotmail.co.jp>
License: Apache-2.0
License-File: LICENSE
Classifier: Development Status :: 1 - Planning
Classifier: License :: OSI Approved :: Apache Software License
Classifier: Programming Language :: Python
Classifier: Topic :: Scientific/Engineering
Classifier: Topic :: Software Development
Requires-Python: >=3.11
